{
  "project_info": {
    "project_number": "1069226145718",
    "firebase_url": "https://alcoholic-3d413.firebaseio.com",
    "project_id": "alcoholic-3d413",
    "storage_bucket": "alcoholic-3d413.appspot.com"
  },
  "client": [
    {
      "client_info": {
        "mobilesdk_app_id": "1:1069226145718:android:3d5c083e01985c5b",
        "android_client_info": {
          "package_name": "com.example.preawbnp.alcoholic"
        }
      },
      "oauth_client": [
        {
          "client_id": "1069226145718-rnug5h61g73tdr5bb010khtrblktq0f1.apps.googleusercontent.com",
          "client_type": 3
        }
      ],
      "api_key": [
        {
          "current_key": "AIzaSyAZEqvtGL_G-0klyb9fMnYNU9haEg8pz10"
        }
      ],
      "services": {
        "analytics_service": {
          "status": 1
        },
        "appinvite_service": {
          "status": 1,
          "other_platform_oauth_client": []
        },
        "ads_service": {
          "status": 2
        }
      }
    }
  ],
  "configuration_version": "1"
}